gridrdf/__init__.py
gridrdf/composition.py
gridrdf/data_explore.py
gridrdf/data_io.py
gridrdf/data_prepare.py
gridrdf/earth_mover_distance.py
gridrdf/extendRDF.py
gridrdf/misc.py
gridrdf/otherRDFs.py
gridrdf/train.py
gridrdf/visualization.py
gridrdf-0.3.0.dist-info/LICENSE.txt
gridrdf-0.3.0.dist-info/METADATA
gridrdf-0.3.0.dist-info/WHEEL
gridrdf-0.3.0.dist-info/top_level.txt
gridrdf-0.3.0.dist-info/RECORD
