Metadata-Version: 2.1
Name: gridrdf
Version: 0.3.0
Summary: Grouped representation of interatomic distances
Home-page: https://git.ecdf.ed.ac.uk/funcmatgroup/gridrdf
Author: jcumby
Author-email: james.cumby@ed.ac.uk
License: MIT
Project-URL: Documentation, https://pyscaffold.org/
Platform: any
Classifier: Development Status :: 4 - Beta
Classifier: Programming Language :: Python
License-File: LICENSE.txt
Requires-Dist: numpy (>=1.19.2)
Requires-Dist: pandas (>=1.1.5)
Requires-Dist: scikit-learn (>=0.22.2)
Requires-Dist: pymatgen (>=2019.7.2)
Requires-Dist: scipy (>=1.5.2)
Requires-Dist: pyemd (>=0.5.1)
Requires-Dist: matminer (>=0.7.4)
Requires-Dist: ElMD (>=0.3.1)
Requires-Dist: numba (>=0.56.4)
Requires-Dist: importlib-metadata ; python_version < "3.8"
Provides-Extra: testing
Requires-Dist: setuptools ; extra == 'testing'
Requires-Dist: pytest ; extra == 'testing'
Requires-Dist: pytest-cov ; extra == 'testing'
